_functiontrace_rs.cpython-314t-x86_64-linux-gnu.so
functiontrace.py
functiontrace-0.5.1.dist-info/METADATA
functiontrace-0.5.1.dist-info/WHEEL
functiontrace-0.5.1.dist-info/entry_points.txt
functiontrace-0.5.1.dist-info/top_level.txt
functiontrace-0.5.1.dist-info/RECORD
functiontrace-0.5.1.dist-info/licenses/LICENSE.md
