Metadata-Version: 2.4
Name: functiontrace
Version: 0.5.1
Summary: A profiling tool that traces your application's execution
Author: Alistair Dobke
Author-email: Matt Bryant <functiontrace@programsareproofs.com>
License-Expression: LicenseRef-Prosperity-Public-License-3.0.0
Project-URL: homepage, https://functiontrace.com
Project-URL: repository, https://gitlab.com/mbryant/functiontrace
Keywords: profiler,debugger
Classifier: Intended Audience :: Developers
Classifier: Topic :: Software Development :: Debuggers
Classifier: Operating System :: Unix
Classifier: Environment :: Console
Classifier: Programming Language :: Python :: 3
Classifier: Programming Language :: Python :: 3 :: Only
Classifier: Programming Language :: Python :: Implementation :: CPython
Requires-Python: >=3.9
License-File: LICENSE.md
Dynamic: license-file
